clidir/__init__.py
clidir/cli.py
latclidir/__init__.py
latclidir/latcli.py
lat-0.0.2.dist-info/METADATA
lat-0.0.2.dist-info/WHEEL
lat-0.0.2.dist-info/entry_points.txt
lat-0.0.2.dist-info/top_level.txt
lat-0.0.2.dist-info/RECORD
