Metadata-Version: 2.1
Name: lat
Version: 0.0.2
Summary: exploring lat-cli
Home-page: UNKNOWN
Author: SimonComputing, Inc.
Author-email: lat@simoncomputing.com
License: MIT
Platform: UNKNOWN
Classifier: License :: OSI Approved :: MIT License
Classifier: Programming Language :: Python :: 3
Classifier: Programming Language :: Python :: 3.10
Requires-Dist: boto3
Requires-Dist: toml
